setup.py
brynq_sdk_maxxton/__init__.py
brynq_sdk_maxxton/maxxton.py
brynq_sdk_maxxton.egg-info/PKG-INFO
brynq_sdk_maxxton.egg-info/SOURCES.txt
brynq_sdk_maxxton.egg-info/dependency_links.txt
brynq_sdk_maxxton.egg-info/not-zip-safe
brynq_sdk_maxxton.egg-info/requires.txt
brynq_sdk_maxxton.egg-info/top_level.txt