Metadata-Version: 1.0
Name: brynq-sdk-maxxton
Version: 1.0.4
Summary: Maxxton wrapper from BrynQ
Home-page: UNKNOWN
Author: BrynQ
Author-email: support@brynq.com
License: BrynQ License
Platform: UNKNOWN
